[{"sleepStartTimestampGMT":"2019-08-08T15:27:00.0","sleepEndTimestampGMT":"2019-08-09T00:06:00.0","calendarDate":"2019-08-09","sleepWindowConfirmationType":"AUTO_CONFIRMED_FINAL","deepSleepSeconds":30120,"lightSleepSeconds":720,"awakeSleepSeconds":300,"unmeasurableSeconds":0,"retro":false},{"sleepStartTimestampGMT":"2019-08-09T14:17:00.0","sleepEndTimestampGMT":"2019-08-10T01:36:00.0","calendarDate":"2019-08-10","sleepWindowConfirmationType":"AUTO_CONFIRMED_FINAL","deepSleepSeconds":40740,"lightSleepSeconds":0,"awakeSleepSeconds":0,"unmeasurableSeconds":0,"retro":false},{"sleepStartTimestampGMT":"2019-08-10T12:52:00.0","sleepEndTimestampGMT":"2019-08-11T00:41:00.0","calendarDate":"2019-08-11","sleepWindowConfirmationType":"AUTO_CONFIRMED_FINAL","deepSleepSeconds":42540,"lightSleepSeconds":0,"awakeSleepSeconds":0,"unmeasurableSeconds":0,"retro":false},{"sleepStartTimestampGMT":"2019-08-11T13:56:00.0","sleepEndTimestampGMT":"2019-08-11T23:41:00.0","calendarDate":"2019-08-12","sleepWindowConfirmationType":"AUTO_CONFIRMED_FINAL","deepSleepSeconds":34080,"lightSleepSeconds":720,"awakeSleepSeconds":300,"unmeasurableSeconds":0,"retro":false},{"sleepStartTimestampGMT":"2019-08-12T12:37:00.0","sleepEndTimestampGMT":"2019-08-12T23:41:00.0","calendarDate":"2019-08-13","sleepWindowConfirmationType":"AUTO_CONFIRMED_FINAL","deepSleepSeconds":39360,"lightSleepSeconds":480,"awakeSleepSeconds":0,"unmeasurableSeconds":0,"retro":false},{"sleepStartTimestampGMT":"2019-08-13T15:24:00.0","sleepEndTimestampGMT":"2019-08-13T23:40:00.0","calendarDate":"2019-08-14","sleepWindowConfirmationType":"AUTO_CONFIRMED_FINAL","deepSleepSeconds":28740,"lightSleepSeconds":720,"awakeSleepSeconds":300,"unmeasurableSeconds":0,"retro":false},{"sleepStartTimestampGMT":"2019-08-14T14:31:00.0","sleepEndTimestampGMT":"2019-08-14T23:32:00.0","calendarDate":"2019-08-15","sleepWindowConfirmationType":"AUTO_CONFIRMED_FINAL","deepSleepSeconds":31440,"lightSleepSeconds":720,"awakeSleepSeconds":300,"unmeasurableSeconds":0,"retro":false},{"sleepStartTimestampGMT":"2019-08-15T12:57:00.0","sleepEndTimestampGMT":"2019-08-15T21:09:00.0","calendarDate":"2019-08-16","sleepWindowConfirmationType":"AUTO_CONFIRMED_FINAL","deepSleepSeconds":27300,"lightSleepSeconds":1920,"awakeSleepSeconds":300,"unmeasurableSeconds":0,"retro":false},{"sleepStartTimestampGMT":"2019-08-16T14:02:00.0","sleepEndTimestampGMT":"2019-08-16T23:03:00.0","calendarDate":"2019-08-17","sleepWindowConfirmationType":"AUTO_CONFIRMED_FINAL","deepSleepSeconds":31380,"lightSleepSeconds":780,"awakeSleepSeconds":300,"unmeasurableSeconds":0,"retro":false},{"sleepStartTimestampGMT":"2019-08-17T15:01:00.0","sleepEndTimestampGMT":"2019-08-18T00:59:00.0","calendarDate":"2019-08-18","sleepWindowConfirmationType":"AUTO_CONFIRMED_FINAL","deepSleepSeconds":33060,"lightSleepSeconds":2520,"awakeSleepSeconds":300,"unmeasurableSeconds":0,"retro":false},{"sleepStartTimestampGMT":"2019-08-18T14:36:00.0","sleepEndTimestampGMT":"2019-08-19T00:26:00.0","calendarDate":"2019-08-19","sleepWindowConfirmationType":"AUTO_CONFIRMED_FINAL","deepSleepSeconds":34380,"lightSleepSeconds":720,"awakeSleepSeconds":300,"unmeasurableSeconds":0,"retro":false},{"sleepStartTimestampGMT":"2019-08-19T12:32:00.0","sleepEndTimestampGMT":"2019-08-19T23:31:00.0","calendarDate":"2019-08-20","sleepWindowConfirmationType":"AUTO_CONFIRMED_FINAL","deepSleepSeconds":38940,"lightSleepSeconds":600,"awakeSleepSeconds":0,"unmeasurableSeconds":0,"retro":false},{"sleepStartTimestampGMT":"2019-08-20T14:46:00.0","sleepEndTimestampGMT":"2019-08-21T00:03:00.0","calendarDate":"2019-08-21","sleepWindowConfirmationType":"AUTO_CONFIRMED_FINAL","deepSleepSeconds":32460,"lightSleepSeconds":660,"awakeSleepSeconds":300,"unmeasurableSeconds":0,"retro":false},{"sleepStartTimestampGMT":"2019-08-21T13:56:00.0","sleepEndTimestampGMT":"2019-08-21T23:33:00.0","calendarDate":"2019-08-22","sleepWindowConfirmationType":"AUTO_CONFIRMED_FINAL","deepSleepSeconds":33600,"lightSleepSeconds":720,"awakeSleepSeconds":300,"unmeasurableSeconds":0,"retro":false},{"sleepStartTimestampGMT":"2019-08-22T13:24:00.0","sleepEndTimestampGMT":"2019-08-23T00:06:00.0","calendarDate":"2019-08-23","sleepWindowConfirmationType":"AUTO_CONFIRMED_FINAL","deepSleepSeconds":37860,"lightSleepSeconds":660,"awakeSleepSeconds":0,"unmeasurableSeconds":0,"retro":false},{"sleepStartTimestampGMT":"2019-08-23T14:37:00.0","sleepEndTimestampGMT":"2019-08-24T01:51:00.0","calendarDate":"2019-08-24","sleepWindowConfirmationType":"AUTO_CONFIRMED_FINAL","deepSleepSeconds":39300,"lightSleepSeconds":1140,"awakeSleepSeconds":0,"unmeasurableSeconds":0,"retro":false},{"sleepStartTimestampGMT":"2019-08-24T14:02:00.0","sleepEndTimestampGMT":"2019-08-25T01:31:00.0","calendarDate":"2019-08-25","sleepWindowConfirmationType":"AUTO_CONFIRMED_FINAL","deepSleepSeconds":41340,"lightSleepSeconds":0,"awakeSleepSeconds":0,"unmeasurableSeconds":0,"retro":false},{"sleepStartTimestampGMT":"2019-08-25T12:42:00.0","sleepEndTimestampGMT":"2019-08-26T00:11:00.0","calendarDate":"2019-08-26","sleepWindowConfirmationType":"AUTO_CONFIRMED_FINAL","deepSleepSeconds":41340,"lightSleepSeconds":0,"awakeSleepSeconds":0,"unmeasurableSeconds":0,"retro":false},{"sleepStartTimestampGMT":"2019-08-26T13:31:00.0","sleepEndTimestampGMT":"2019-08-26T23:56:00.0","calendarDate":"2019-08-27","sleepWindowConfirmationType":"AUTO_CONFIRMED_FINAL","deepSleepSeconds":36480,"lightSleepSeconds":720,"awakeSleepSeconds":300,"unmeasurableSeconds":0,"retro":false},{"sleepStartTimestampGMT":"2019-08-27T14:34:00.0","sleepEndTimestampGMT":"2019-08-27T23:34:00.0","calendarDate":"2019-08-28","sleepWindowConfirmationType":"AUTO_CONFIRMED_FINAL","deepSleepSeconds":31380,"lightSleepSeconds":720,"awakeSleepSeconds":300,"unmeasurableSeconds":0,"retro":false},{"sleepStartTimestampGMT":"2019-08-28T13:39:00.0","sleepEndTimestampGMT":"2019-08-28T23:41:00.0","calendarDate":"2019-08-29","sleepWindowConfirmationType":"AUTO_CONFIRMED_FINAL","deepSleepSeconds":35100,"lightSleepSeconds":720,"awakeSleepSeconds":300,"unmeasurableSeconds":0,"retro":false},{"sleepStartTimestampGMT":"2019-08-29T14:55:00.0","sleepEndTimestampGMT":"2019-08-30T00:12:00.0","calendarDate":"2019-08-30","sleepWindowConfirmationType":"AUTO_CONFIRMED_FINAL","deepSleepSeconds":32400,"lightSleepSeconds":720,"awakeSleepSeconds":300,"unmeasurableSeconds":0,"retro":false},{"sleepStartTimestampGMT":"2019-08-30T15:20:00.0","sleepEndTimestampGMT":"2019-08-31T00:56:00.0","calendarDate":"2019-08-31","sleepWindowConfirmationType":"AUTO_CONFIRMED_FINAL","deepSleepSeconds":33540,"lightSleepSeconds":720,"awakeSleepSeconds":300,"unmeasurableSeconds":0,"retro":false},{"sleepStartTimestampGMT":"2019-08-31T14:02:00.0","sleepEndTimestampGMT":"2019-09-01T01:41:00.0","calendarDate":"2019-09-01","sleepWindowConfirmationType":"AUTO_CONFIRMED_FINAL","deepSleepSeconds":41940,"lightSleepSeconds":0,"awakeSleepSeconds":0,"unmeasurableSeconds":0,"retro":false},{"sleepStartTimestampGMT":"2019-09-01T12:37:00.0","sleepEndTimestampGMT":"2019-09-01T23:41:00.0","calendarDate":"2019-09-02","sleepWindowConfirmationType":"AUTO_CONFIRMED_FINAL","deepSleepSeconds":39480,"lightSleepSeconds":360,"awakeSleepSeconds":0,"unmeasurableSeconds":0,"retro":false},{"sleepStartTimestampGMT":"2019-09-02T12:37:00.0","sleepEndTimestampGMT":"2019-09-02T23:46:00.0","calendarDate":"2019-09-03","sleepWindowConfirmationType":"AUTO_CONFIRMED_FINAL","deepSleepSeconds":40080,"lightSleepSeconds":60,"awakeSleepSeconds":0,"unmeasurableSeconds":0,"retro":false},{"sleepStartTimestampGMT":"2019-09-03T14:43:00.0","sleepEndTimestampGMT":"2019-09-04T00:10:00.0","calendarDate":"2019-09-04","sleepWindowConfirmationType":"AUTO_CONFIRMED_FINAL","deepSleepSeconds":33000,"lightSleepSeconds":720,"awakeSleepSeconds":300,"unmeasurableSeconds":0,"retro":false},{"sleepStartTimestampGMT":"2019-09-04T13:51:00.0","sleepEndTimestampGMT":"2019-09-04T23:24:00.0","calendarDate":"2019-09-05","sleepWindowConfirmationType":"AUTO_CONFIRMED_FINAL","deepSleepSeconds":33360,"lightSleepSeconds":720,"awakeSleepSeconds":300,"unmeasurableSeconds":0,"retro":false},{"sleepStartTimestampGMT":"2019-09-05T13:57:00.0","sleepEndTimestampGMT":"2019-09-05T23:56:00.0","calendarDate":"2019-09-06","sleepWindowConfirmationType":"AUTO_CONFIRMED_FINAL","deepSleepSeconds":35520,"lightSleepSeconds":420,"awakeSleepSeconds":0,"unmeasurableSeconds":0,"retro":false},{"sleepStartTimestampGMT":"2019-09-06T14:12:00.0","sleepEndTimestampGMT":"2019-09-07T01:41:00.0","calendarDate":"2019-09-07","sleepWindowConfirmationType":"AUTO_CONFIRMED_FINAL","deepSleepSeconds":41340,"lightSleepSeconds":0,"awakeSleepSeconds":0,"unmeasurableSeconds":0,"retro":false},{"sleepStartTimestampGMT":"2019-09-07T14:27:00.0","sleepEndTimestampGMT":"2019-09-08T01:36:00.0","calendarDate":"2019-09-08","sleepWindowConfirmationType":"AUTO_CONFIRMED_FINAL","deepSleepSeconds":40140,"lightSleepSeconds":0,"awakeSleepSeconds":0,"unmeasurableSeconds":0,"retro":false},{"sleepStartTimestampGMT":"2019-09-08T13:27:00.0","sleepEndTimestampGMT":"2019-09-09T00:11:00.0","calendarDate":"2019-09-09","sleepWindowConfirmationType":"AUTO_CONFIRMED_FINAL","deepSleepSeconds":38400,"lightSleepSeconds":240,"awakeSleepSeconds":0,"unmeasurableSeconds":0,"retro":false},{"sleepStartTimestampGMT":"2019-09-09T12:42:00.0","sleepEndTimestampGMT":"2019-09-09T23:56:00.0","calendarDate":"2019-09-10","sleepWindowConfirmationType":"AUTO_CONFIRMED_FINAL","deepSleepSeconds":40440,"lightSleepSeconds":0,"awakeSleepSeconds":0,"unmeasurableSeconds":0,"retro":false},{"sleepStartTimestampGMT":"2019-09-10T13:59:00.0","sleepEndTimestampGMT":"2019-09-10T23:44:00.0","calendarDate":"2019-09-11","sleepWindowConfirmationType":"AUTO_CONFIRMED_FINAL","deepSleepSeconds":34200,"lightSleepSeconds":900,"awakeSleepSeconds":0,"unmeasurableSeconds":0,"retro":false},{"sleepStartTimestampGMT":"2019-09-11T12:51:00.0","sleepEndTimestampGMT":"2019-09-11T23:41:00.0","calendarDate":"2019-09-12","sleepWindowConfirmationType":"AUTO_CONFIRMED_FINAL","deepSleepSeconds":38460,"lightSleepSeconds":540,"awakeSleepSeconds":0,"unmeasurableSeconds":0,"retro":false},{"sleepStartTimestampGMT":"2019-09-12T14:15:00.0","sleepEndTimestampGMT":"2019-09-13T00:11:00.0","calendarDate":"2019-09-13","sleepWindowConfirmationType":"AUTO_CONFIRMED_FINAL","deepSleepSeconds":35340,"lightSleepSeconds":420,"awakeSleepSeconds":0,"unmeasurableSeconds":0,"retro":false},{"sleepStartTimestampGMT":"2019-09-13T12:42:00.0","sleepEndTimestampGMT":"2019-09-14T00:06:00.0","calendarDate":"2019-09-14","sleepWindowConfirmationType":"AUTO_CONFIRMED_FINAL","deepSleepSeconds":39900,"lightSleepSeconds":1140,"awakeSleepSeconds":0,"unmeasurableSeconds":0,"retro":false},{"sleepStartTimestampGMT":"2019-10-05T16:01:00.0","sleepEndTimestampGMT":"2019-10-05T23:32:00.0","calendarDate":"2019-10-06","sleepWindowConfirmationType":"AUTO_CONFIRMED_FINAL","deepSleepSeconds":26280,"lightSleepSeconds":480,"awakeSleepSeconds":300,"unmeasurableSeconds":0,"retro":false},{"sleepStartTimestampGMT":"2019-10-06T12:52:00.0","sleepEndTimestampGMT":"2019-10-07T00:31:00.0","calendarDate":"2019-10-07","sleepWindowConfirmationType":"AUTO_CONFIRMED_FINAL","deepSleepSeconds":41940,"lightSleepSeconds":0,"awakeSleepSeconds":0,"unmeasurableSeconds":0,"retro":false},{"sleepStartTimestampGMT":"2019-10-07T12:37:00.0","sleepEndTimestampGMT":"2019-10-07T23:46:00.0","calendarDate":"2019-10-08","sleepWindowConfirmationType":"AUTO_CONFIRMED_FINAL","deepSleepSeconds":39960,"lightSleepSeconds":180,"awakeSleepSeconds":0,"unmeasurableSeconds":0,"retro":false},{"sleepStartTimestampGMT":"2019-10-08T14:41:00.0","sleepEndTimestampGMT":"2019-10-08T23:29:00.0","calendarDate":"2019-10-09","sleepWindowConfirmationType":"AUTO_CONFIRMED_FINAL","deepSleepSeconds":30660,"lightSleepSeconds":720,"awakeSleepSeconds":300,"unmeasurableSeconds":0,"retro":false},{"sleepStartTimestampGMT":"2019-10-09T14:02:00.0","sleepEndTimestampGMT":"2019-10-10T01:36:00.0","calendarDate":"2019-10-10","sleepWindowConfirmationType":"AUTO_CONFIRMED_FINAL","deepSleepSeconds":41640,"lightSleepSeconds":0,"awakeSleepSeconds":0,"unmeasurableSeconds":0,"retro":false},{"sleepStartTimestampGMT":"2019-10-10T12:54:00.0","sleepEndTimestampGMT":"2019-10-10T23:21:00.0","calendarDate":"2019-10-11","sleepWindowConfirmationType":"AUTO_CONFIRMED_FINAL","deepSleepSeconds":36780,"lightSleepSeconds":840,"awakeSleepSeconds":0,"unmeasurableSeconds":0,"retro":false},{"sleepStartTimestampGMT":"2019-10-11T14:00:00.0","sleepEndTimestampGMT":"2019-10-11T22:00:00.0","calendarDate":"2019-10-12","sleepWindowConfirmationType":"UNCONFIRMED","retro":false}]